Design.v
`timescale 1ns / 1ps
//////////////////////////////////////////////////////////////////////////////////
// Company: 
// Engineer: 
// 
// Create Date: 13.04.2026 12:18:35
// Design Name: 
// Module Name: pEncoder
// Project Name: 
// Target Devices: 
// Tool Versions: 
// Description: 
// 
// Dependencies: 
// 
// Revision:
// Revision 0.01 - File Created
// Additional Comments:
// 
//////////////////////////////////////////////////////////////////////////////////


module pEncoder(
    input a_i, 
    input b_i, 
    input c_i, 
    input d_i, 
    output reg x_o, 
    output reg y_o
);

always@(*)
//if(a_i === 1'bx || b_i === 1'bx || c_i === 1'bx || d_i === 1'bx) begin //don't care handling
//   x_o = 1'bx;
//   y_o = 1'bx;
//end
//in real hardware, x does not exist-- simulation only design
if((a_i | b_i | c_i | d_i) == 0) begin //all 0 handling
   x_o = 1'b0;
   y_o = 1'b0;
end
else if(a_i) begin //Data line A
   x_o = 1'b0;
   y_o = 1'b0;
end
else if(b_i) begin //Data line B
   x_o = 1'b0;
   y_o = 1'b1;
end
else if(c_i) begin //Data line C
   x_o = 1'b1;
   y_o = 1'b0;
end
else begin //Data line D
   x_o = 1'b1;
   y_o = 1'b1;
end

endmodule

Testbench.v
`timescale 1ns / 1ps
//////////////////////////////////////////////////////////////////////////////////
// Company: 
// Engineer: 
// 
// Create Date: 13.04.2026 12:19:03
// Design Name: 
// Module Name: tb_pEncoder
// Project Name: 
// Target Devices: 
// Tool Versions: 
// Description: 
// 
// Dependencies: 
// 
// Revision:
// Revision 0.01 - File Created
// Additional Comments:
// 
//////////////////////////////////////////////////////////////////////////////////


module tb_pEncoder();
reg a_i;
reg b_i;
reg c_i;
reg d_i;
wire x_o;
wire y_o;

//instantiation
pEncoder UUT(.a_i(a_i), 
    .b_i(b_i), 
    .c_i(c_i), 
    .d_i(d_i), 
    .x_o(x_o), 
    .y_o(y_o));

//feeding
initial begin 
a_i = 1'b0; 
b_i = 1'b0; 
c_i = 1'b0; 
d_i = 1'b0; //all 0s
$display("Data line: All 0s");
#5 a_i = 1'b1; 
   b_i = 1'b0; 
   c_i = 1'b0; 
   d_i = 1'b0; //A
$display("Data line: A");
#5 a_i = 1'b0; 
   b_i = 1'b1; 
   c_i = 1'b0; 
   d_i = 1'b0; //B
$display("Data line: B");
#5 a_i = 1'b0; 
   b_i = 1'b0; 
   c_i = 1'b1; 
   d_i = 1'b0; //C
$display("Data line: C");
#5 a_i = 1'b0; 
   b_i = 1'b0; 
   c_i = 1'b0; 
   d_i = 1'b1; //D
$display("Data line: D");
#5 a_i = 1'bx; 
   b_i = 1'b1; 
   c_i = 1'b0; 
   d_i = 1'b0; //Priority is X, remaining data lines include 1
$display("Data line: X100");
#5 a_i = 1'b1; 
   b_i = 1'bx; 
   c_i = 1'b0; 
   d_i = 1'b0; //Priority is 1, remaining data lines include X
$display("Data line: 1X00");
#5 a_i = 1'b0; 
   b_i = 1'bx; 
   c_i = 1'b0; 
   d_i = 1'b0; //one data line X, rest 0
$display("Data line: one X, rest 0");
#5 a_i = 1'bx; 
   b_i = 1'bx; 
   c_i = 1'bx; 
   d_i = 1'bx; //all X
$display("Data line: All X");
#5 a_i = 1'b1; 
   b_i = 1'b1; 
   c_i = 1'b1; 
   d_i = 1'b1; //all 1s
$display("Data line: All 1s");
end

//capture
initial begin
$monitor("Time: %0t | A: %b, B: %b, C: %b, D: %b | X: %b, Y: %b", $time, a_i, b_i, c_i, d_i, x_o, y_o);
$dumpfile("pEncoder.vcd");
$dumpvars(0, tb_pEncoder);
end

endmodule

pEncoder.vcd
$date
   Mon Apr 13 13:31:03 2026
$end

$version
  2025.2
  $dumpfile ("pEncoder.vcd") 
$end

$timescale
  1ps
$end

$scope module tb_pEncoder $end
$var reg 1 ! a_i $end
$var reg 1 " b_i $end
$var reg 1 # c_i $end
$var reg 1 $ d_i $end
$var wire 1 % x_o $end
$var wire 1 & y_o $end
$scope module UUT $end
$var wire 1 ' a_i $end
$var wire 1 ( b_i $end
$var wire 1 ) c_i $end
$var wire 1 * d_i $end
$var reg 1 + x_o $end
$var reg 1 , y_o $end
$upscope $end
$upscope $end
$enddefinitions $end

#0
$dumpvars
0!
0"
0#
0$
0%
0&
0'
0(
0)
0*
0+
0,
$end

#5000
1!
1'

#10000
0!
1"
1&
0'
1(
1,

#15000
0"
1#
1%
0&
0(
1)
1+
0,

#20000
0#
1$
1&
0)
1*
1,

#25000
x!
1"
0$
0%
x'
1(
0*
0+

#30000
1!
x"
0&
1'
x(
0,

#35000
0!
1%
1&
0'
1+
1,

#40000
x!
x#
x$
x'
x)
x*

#45000
1!
1"
1#
1$
0%
0&
1'
1(
1)
1*
0+
0,
